globalwarmingpotentials/__init__.py
globalwarmingpotentials/_version.py
globalwarmingpotentials/globalwarmingpotentials.csv
globalwarmingpotentials-0.11.1.dist-info/LICENSE
globalwarmingpotentials-0.11.1.dist-info/METADATA
globalwarmingpotentials-0.11.1.dist-info/WHEEL
globalwarmingpotentials-0.11.1.dist-info/top_level.txt
globalwarmingpotentials-0.11.1.dist-info/RECORD
