Metadata-Version: 2.1
Name: globalwarmingpotentials
Version: 0.11.1
Summary: Global warming potentials of greenhouse gases from various IPCC reports
Home-page: https://github.com/openclimatedata/globalwarmingpotentials
Author: Robert Gieseke
Author-email: rob.g@web.de
License: CC0
Keywords: climate research,greenhouse gases,global warming potentials,climate change
Platform: any
Classifier: Development Status :: 3 - Alpha
Classifier: Intended Audience :: Developers
Classifier: Operating System :: OS Independent
Classifier: Programming Language :: Python :: 3.6
Classifier: Programming Language :: Python :: 3.7
Classifier: Programming Language :: Python :: 3.8
Classifier: Programming Language :: Python :: 3.9
License-File: LICENSE
